Metadata-Version: 2.1
Name: lingueeParser
Version: 1.0.2
Summary: Linguee translation parser
Home-page: https://github.com/Schlaumra/linguee-parser
Author: schlaumra
Author-email: amhof13raphael10@gmail.com
License: GPL3
Platform: UNKNOWN
License-File: LICENSE
